MANIFEST.in
README.md
setup.py
esper/__init__.py
esper/common.py
esper/configure.py
esper/jupyter.py
esper/logging.py
esper/models.py
esper/notifier.py
esper/postgres.py
esper/queries.py
esper/scanner.py
esper/scanner_bench.py
esper/spark.py
esper/util.py
esper/video.py
esper/views.py
esper/django/gunicorn_conf.py
esper/django/manage.py
esper/django/django_settings/__init__.py
esper/django/django_settings/settings.py
esper/django/django_settings/urls.py
esper/django/django_settings/wsgi.py
esper/django/server/__init__.py
esper/django/server/admin.py
esper/django/server/apps.py
esper/django/server/models.py
esper/django/server/tests.py
esper/django/server/urls.py
esper/django/server/views.py
esper/django/server/management/__init__.py
esper/django/server/management/commands/__init__.py
esper/django/server/management/commands/run.py
esper/django/server/templates/base.html
esper/django/server/templates/index.html
esper/django/ui/.dockerignore
esper/django/ui/.gitignore
esper/django/ui/favicon-loading.ico
esper/django/ui/favicon.ico
esper/django/ui/package-lock.json
esper/django/ui/package.json
esper/django/ui/webpack.config.js
esper/django/ui/bundles/89889688147bd7575d6327160d64e760.svg
esper/django/ui/bundles/styles.css
esper/django/ui/bundles/styles.css.map
esper/django/ui/bundles/styles.js
esper/django/ui/bundles/styles.js.map
esper/django/ui/bundles/web.js
esper/django/ui/bundles/web.js.map
esper/django/ui/bundles/webpack-stats.json
esper/django/ui/css/bootstrap.scss
esper/django/ui/css/main.scss
esper/django/ui/css/search-input.scss
esper/django/ui/css/sidebar.scss
esper/django/ui/images/dan_spinning.gif
esper/django/ui/images/haotian_spinning.gif
esper/django/ui/images/james_spinning.gif
esper/django/ui/images/kayvon_spinning.gif
esper/django/ui/images/maneesh_spinning.gif
esper/django/ui/images/spinner.gif
esper/django/ui/images/will_spinning.gif
esper/django/ui/js/Consumer.jsx
esper/django/ui/js/Provider.jsx
esper/django/ui/js/SearchInput.jsx
esper_video.egg-info/PKG-INFO
esper_video.egg-info/SOURCES.txt
esper_video.egg-info/dependency_links.txt
esper_video.egg-info/entry_points.txt
esper_video.egg-info/not-zip-safe
esper_video.egg-info/requires.txt
esper_video.egg-info/top_level.txt