Metadata-Version: 1.0
Name: esper-video
Version: 0.1.0
Summary: A framework for end-to-end video analytics
Home-page: http://github.com/scanner-research/esper
Author: Will Crichton
Author-email: wcrichto@cs.stanford.edu
License: Apache 2.0
Platform: UNKNOWN
